shellsage/__init__.py
shellsage/cli.py
shellsage/utils.py
shellsage/docs/commands.txt
shellsage/docs/grep.txt
shellsage/docs/ls.txt
shellsage/docs/ps.txt
shellsage/embeddings/shell_docs.index
shellsage/embeddings/shell_docs_meta.hash
shellsage/embeddings/shell_docs_meta.json
shellsage_cli-0.2.4.dist-info/licenses/LICENSE
shellsage_cli-0.2.4.dist-info/METADATA
shellsage_cli-0.2.4.dist-info/WHEEL
shellsage_cli-0.2.4.dist-info/entry_points.txt
shellsage_cli-0.2.4.dist-info/top_level.txt
shellsage_cli-0.2.4.dist-info/RECORD
